pyarma-0.500.3.dist-info/RECORD
pyarma-0.500.3.dist-info/LICENSE
pyarma-0.500.3.dist-info/WHEEL
pyarma-0.500.3.dist-info/NOTICE
pyarma-0.500.3.dist-info/top_level.txt
pyarma-0.500.3.dist-info/METADATA
pyarma/__init__.py
pyarma/pyarma.cpython-36m-darwin.so
pyarma/include/armadillo
pyarma/include/armadillo_bits/op_powmat_meat.hpp
pyarma/include/armadillo_bits/spglue_plus_bones.hpp
pyarma/include/armadillo_bits/op_logmat_meat.hpp
pyarma/include/armadillo_bits/op_prod_bones.hpp
pyarma/include/armadillo_bits/fn_sort.hpp
pyarma/include/armadillo_bits/op_cx_scalar_bones.hpp
pyarma/include/armadillo_bits/fn_index_max.hpp
pyarma/include/armadillo_bits/op_sum_bones.hpp
pyarma/include/armadillo_bits/fn_numel.hpp
pyarma/include/armadillo_bits/csv_name.hpp
pyarma/include/armadillo_bits/op_htrans_bones.hpp
pyarma/include/armadillo_bits/spop_mean_bones.hpp
pyarma/include/armadillo_bits/fn_orth_null.hpp
pyarma/include/armadillo_bits/op_cov_meat.hpp
pyarma/include/armadillo_bits/op_relational_bones.hpp
pyarma/include/armadillo_bits/wall_clock_bones.hpp
pyarma/include/armadillo_bits/spglue_times_meat.hpp
pyarma/include/armadillo_bits/glue_trapz_bones.hpp
pyarma/include/armadillo_bits/glue_affmul_meat.hpp
pyarma/include/armadillo_bits/glue_join_meat.hpp
pyarma/include/armadillo_bits/glue_cov_bones.hpp
pyarma/include/armadillo_bits/op_cumprod_bones.hpp
pyarma/include/armadillo_bits/fn_rank.hpp
pyarma/include/armadillo_bits/fn_trig.hpp
pyarma/include/armadillo_bits/spglue_kron_bones.hpp
pyarma/include/armadillo_bits/fn_all.hpp
pyarma/include/armadillo_bits/spop_var_meat.hpp
pyarma/include/armadillo_bits/eglue_core_meat.hpp
pyarma/include/armadillo_bits/op_sort_bones.hpp
pyarma/include/armadillo_bits/subview_cube_bones.hpp
pyarma/include/armadillo_bits/spop_trimat_meat.hpp
pyarma/include/armadillo_bits/spop_strans_bones.hpp
pyarma/include/armadillo_bits/spop_repmat_meat.hpp
pyarma/include/armadillo_bits/fn_eig_pair.hpp
pyarma/include/armadillo_bits/fn_trace.hpp
pyarma/include/armadillo_bits/promote_type.hpp
pyarma/include/armadillo_bits/fn_wishrnd.hpp
pyarma/include/armadillo_bits/MapMat_meat.hpp
pyarma/include/armadillo_bits/access.hpp
