Metadata-Version: 2.1
Name: pyarma
Version: 0.500.3
Summary: Linear algebra library for Python, with emphasis on ease of use
Home-page: https://pyarma.sourceforge.io
Author: Jason Rumengan
Author-email: jason.rumengan@connect.qut.edu.au
License: UNKNOWN
Project-URL: Documentation, https://pyarma.sourceforge.io/docs.html
Project-URL: Source, https://gitlab.com/jason-rumengan/pyarma
Project-URL: Tracker, https://gitlab.com/jason-rumengan/pyarma/issues
Keywords: linear algebra scientific computing pyarma pyarmadillo armadillo arma c++ pybind11 library
Platform: UNKNOWN
Classifier: Development Status :: 4 - Beta
Classifier: Intended Audience :: Science/Research
Classifier: Intended Audience :: Developers
Classifier: Topic :: Scientific/Engineering :: Mathematics
Classifier: Topic :: Software Development :: Libraries :: Python Modules
Classifier: Programming Language :: C++
Classifier: Programming Language :: Python :: 3.6
Classifier: Programming Language :: Python :: 3.7
Classifier: Programming Language :: Python :: 3.8
Classifier: Programming Language :: Python :: 3.9
Classifier: License :: OSI Approved :: Apache Software License
Classifier: Operating System :: OS Independent
Requires-Python: >=3.6.0
License-File: LICENSE
License-File: NOTICE
